lazy_calculator/__init__.py
lazy_calculator/factorial.py
lazy_calculator/fibonacci.py
lazy_calculator-0.1.5.dist-info/LICENSE
lazy_calculator-0.1.5.dist-info/METADATA
lazy_calculator-0.1.5.dist-info/WHEEL
lazy_calculator-0.1.5.dist-info/RECORD
