Metadata-Version: 2.1
Name: lazy-calculator
Version: 0.1.5
Summary: A Powerful Python Library for Effortless Calculations
License: Apache-2.0
Author: ppirch
Requires-Python: >=3.9,<4.0
Classifier: License :: OSI Approved :: Apache Software License
Classifier: Programming Language :: Python :: 3
Classifier: Programming Language :: Python :: 3.9
Classifier: Programming Language :: Python :: 3.10
Classifier: Programming Language :: Python :: 3.11
